vk_bot/__about__.py
vk_bot/__init__.py
vk_bot/bot.py
vk_bot/dispatcher.py
vk_bot/ext/__init__.py
vk_bot/ext/cmd.py
vk_bot/ext/testing.py
vk_bot-0.6.1.dist-info/METADATA
vk_bot-0.6.1.dist-info/RECORD
vk_bot-0.6.1.dist-info/WHEEL
vk_bot-0.6.1.dist-info/top_level.txt
