Metadata-Version: 1.0
Name: vk-bot
Version: 0.6.1
Summary: Py3 VK bot builder.
Home-page: https://github.com/Suenweek/vk-bot
Author: Roman Novatorov
Author-email: roman.novatorov@gmail.com
License: UNKNOWN
Platform: UNKNOWN
